flask_arxiv_feed_fixer/__init__.py
flask_arxiv_feed_fixer-0.1.0.dist-info/WHEEL
flask_arxiv_feed_fixer-0.1.0.dist-info/METADATA
flask_arxiv_feed_fixer-0.1.0.dist-info/RECORD
