Metadata-Version: 2.1
Name: flask-arxiv-feed-fixer
Version: 0.1.0
Summary: 
Author: Andrew Kail
Author-email: andrew.a.kail@gmail.com
Requires-Python: >=3.8,<4.0
Classifier: Programming Language :: Python :: 3
Classifier: Programming Language :: Python :: 3.8
Requires-Dist: flask (>=1.1.2,<2.0.0)
Requires-Dist: requests (>=2.25.0,<3.0.0)
